velocycle/__init__.py
velocycle/angularspeed.py
velocycle/cycle.py
velocycle/phase_inference_guide.py
velocycle/phase_inference_model.py
velocycle/phases.py
velocycle/plots.py
velocycle/preprocessing.py
velocycle/utils.py
velocycle/velocity_inference_guide.py
velocycle/velocity_inference_model.py
velocycle-0.1.0.5.dist-info/LICENSE.md
velocycle-0.1.0.5.dist-info/METADATA
velocycle-0.1.0.5.dist-info/WHEEL
velocycle-0.1.0.5.dist-info/top_level.txt
velocycle-0.1.0.5.dist-info/RECORD
